allure_pytest_logger/__init__.py
allure_pytest_logger/plugin.py
allure_pytest_logger/py.typed
allure_pytest_logger-1.0.1.dist-info/entry_points.txt
allure_pytest_logger-1.0.1.dist-info/LICENSE
allure_pytest_logger-1.0.1.dist-info/WHEEL
allure_pytest_logger-1.0.1.dist-info/METADATA
allure_pytest_logger-1.0.1.dist-info/RECORD
